Python_Road.py
Python_Road-0.0.0.4.dist-info/METADATA
Python_Road-0.0.0.4.dist-info/WHEEL
Python_Road-0.0.0.4.dist-info/top_level.txt
Python_Road-0.0.0.4.dist-info/RECORD
