Metadata-Version: 2.1
Name: Python-Road
Version: 0.0.0.4
Summary: 模块
Author: sunruiyang
Author-email: dogsmallsmile@163.com
